diwasp/__init__.py
diwasp/core.py
diwasp/spectrum.py
diwasp/transfer.py
diwasp/types.py
diwasp/utils.py
diwasp/wrapper.py
diwasp/methods/__init__.py
diwasp/methods/base.py
diwasp/methods/bdm.py
diwasp/methods/dftm.py
diwasp/methods/emep.py
diwasp/methods/emlm.py
diwasp/methods/imlm.py
diwasp-0.1.0.dist-info/licenses/LICENSE
diwasp-0.1.0.dist-info/METADATA
diwasp-0.1.0.dist-info/WHEEL
diwasp-0.1.0.dist-info/top_level.txt
diwasp-0.1.0.dist-info/RECORD
