Metadata-Version: 2.4
Name: diwasp
Version: 0.1.0
Summary: DIrectional WAve SPectrum analysis - Python port of the DIWASP Matlab toolbox
Author-email: David Johnson <david.johnson@uwa.edu.au>
Maintainer-email: Your Name <your.email@example.com>
License: MIT
Project-URL: Homepage, https://github.com/yourusername/diwasp-python
Project-URL: Documentation, https://diwasp-python.readthedocs.io
Project-URL: Repository, https://github.com/yourusername/diwasp-python
Keywords: waves,oceanography,spectral analysis,directional spectrum
Classifier: Development Status :: 3 - Alpha
Classifier: Intended Audience :: Science/Research
Classifier: License :: OSI Approved :: MIT License
Classifier: Operating System :: OS Independent
Classifier: Programming Language :: Python :: 3
Classifier: Programming Language :: Python :: 3.9
Classifier: Programming Language :: Python :: 3.10
Classifier: Programming Language :: Python :: 3.11
Classifier: Programming Language :: Python :: 3.12
Classifier: Topic :: Scientific/Engineering :: Physics
Requires-Python: >=3.9
License-File: LICENSE
Requires-Dist: numpy>=1.20
Requires-Dist: scipy>=1.7
Requires-Dist: xarray>=0.19
Requires-Dist: wavespectra>=4.0
Requires-Dist: pandas>=1.3
Provides-Extra: dev
Requires-Dist: pytest>=7.0; extra == "dev"
Requires-Dist: pytest-cov>=4.0; extra == "dev"
Requires-Dist: black>=23.0; extra == "dev"
Requires-Dist: ruff>=0.1; extra == "dev"
Requires-Dist: mypy>=1.0; extra == "dev"
Provides-Extra: docs
Requires-Dist: sphinx>=6.0; extra == "docs"
Requires-Dist: pydata-sphinx-theme>=0.13; extra == "docs"
Requires-Dist: myst-parser>=2.0; extra == "docs"
Requires-Dist: sphinx-gallery>=0.14; extra == "docs"
Dynamic: license-file
